alphabench/__init__.py
alphabench-0.1.0.dist-info/licenses/LICENSE
alphabench-0.1.0.dist-info/METADATA
alphabench-0.1.0.dist-info/WHEEL
alphabench-0.1.0.dist-info/top_level.txt
alphabench-0.1.0.dist-info/RECORD
